Metadata-Version: 1.1
Name: bjp-make
Version: 0.1
Summary: Wrapping code for project execution.
Home-page: https://github.com/bperry12/bjp_python/tree/master/bjp_make
Author: Bryan J. Perry
Author-email: perryb@mit.edu
License: MIT
Platform: UNKNOWN
Classifier: Development Status :: 2 - Pre-Alpha
Classifier: License :: OSI Approved :: MIT License
Classifier: Natural Language :: English
Classifier: Programming Language :: Python :: 2.7
Classifier: Topic :: Utilities
